phomemo_printer/ESCPOS_constants.py
phomemo_printer/ESCPOS_printer.py
phomemo_printer/__init__.py
phomemo_printer/command_line.py
phomemo_printer/version.py
phomemo_printer/pixel_sans/__init__.py
phomemo_printer/pixel_sans/alphabet.py
phomemo_printer/pixel_sans/charset.py
phomemo_printer/pixel_sans/digits.py
phomemo_printer/pixel_sans/emoji.py
phomemo_printer/pixel_sans/symbols.py
phomemo_printer-1.0.5.dist-info/LICENSE
phomemo_printer-1.0.5.dist-info/METADATA
phomemo_printer-1.0.5.dist-info/WHEEL
phomemo_printer-1.0.5.dist-info/entry_points.txt
phomemo_printer-1.0.5.dist-info/top_level.txt
phomemo_printer-1.0.5.dist-info/RECORD
