Metadata-Version: 2.1
Name: phomemo_printer
Version: 1.0.5
Summary: Print text as a raster bit image from a Phomemo printer.
Home-page: https://github.com/hkeward/phomemo_printer
Author: Heather Ward
Author-email: heather.ward13@gmail.com
License: gpl-2.0
Classifier: Programming Language :: Python :: 3
Classifier: License :: OSI Approved :: GNU General Public License v2 (GPLv2)
Classifier: Operating System :: Unix
License-File: LICENSE
Requires-Dist: argparse
Requires-Dist: Pillow
